NN4OCMSP/__init__.py
NN4OCMSP/dataset.py
NN4OCMSP/functions.py
NN4OCMSP/data/HVAC_data_set.csv
NN4OCMSP-1.1.1.dist-info/METADATA
NN4OCMSP-1.1.1.dist-info/WHEEL
NN4OCMSP-1.1.1.dist-info/top_level.txt
NN4OCMSP-1.1.1.dist-info/RECORD
