Metadata-Version: 2.1
Name: NN4OCMSP
Version: 1.1.1
Summary: Neural network out-of-control signal interpretation in multiple stream processes
Home-page: https://github.com/unina-sfere/NN4OCMSP
Author: Antonio Lepore, Biagio Palumbo, Gianluca Sposito
Author-email: antonio.lepore@unina.it, biagio.palumbo@unina.it, gianluca.sposito@unina.it
License: GNU General Public License v3.0
Keywords: Out-of-control signal interpretation,Artificial neural networks,Multiple stream process,Multi-label classification,Railway HVAC systems
Platform: UNKNOWN
Classifier: Intended Audience :: Education
Classifier: Intended Audience :: Science/Research
Classifier: Intended Audience :: Manufacturing
Classifier: Intended Audience :: Developers
Classifier: Programming Language :: Python :: 3
Classifier: Operating System :: MacOS :: MacOS X
Classifier: Operating System :: Microsoft :: Windows
Requires-Dist: numpy
Requires-Dist: matplotlib
Requires-Dist: sklearn
Requires-Dist: tensorflow
Requires-Dist: keras
